geodata/__init__.py
geodata/_version.py
geodata/config.py
geodata/convert.py
geodata/cutout.py
geodata/dataset.py
geodata/logging.py
geodata/mask.py
geodata/plot.py
geodata/preparation.py
geodata/resource.py
geodata/utils.py
geodata/wind.py
geodata/datasets/__init__.py
geodata/datasets/era5.py
geodata/datasets/merra2.py
geodata/model/__init__.py
geodata/model/_base.py
geodata/model/wind/__init__.py
geodata/model/wind/_base.py
geodata/model/wind/extrapolate.py
geodata/model/wind/interpolate.py
geodata/pv/__init__.py
geodata/pv/irradiation.py
geodata/pv/orientation.py
geodata/pv/solar_panel_model.py
geodata/pv/solar_position.py
geodata_re-0.1.0.dist-info/LICENSE
geodata_re-0.1.0.dist-info/METADATA
geodata_re-0.1.0.dist-info/WHEEL
geodata_re-0.1.0.dist-info/top_level.txt
geodata_re-0.1.0.dist-info/RECORD
