Metadata-Version: 2.1
Name: geodata-re
Version: 0.1.0
Summary: Geospatial Data Collection and Pre-Analysis Tools
Author-email: Michael Davidson <mrdavidson@ucsd.edu>, Xiqiang Liu <9440183+xiqiangliu@users.noreply.github.com>
License: GPLv3
Requires-Python: >=3.10
License-File: LICENSE
Requires-Dist: numpy <2
Requires-Dist: scipy >=1.8.0
Requires-Dist: pandas >=2.2.3
Requires-Dist: bottleneck >=1.3.6
Requires-Dist: numexpr ==2.10.1
Requires-Dist: xarray >=2024.9.0
Requires-Dist: netcdf4 >=1.7.1.post2
Requires-Dist: boto3 ==1.26.46
Requires-Dist: toolz >=0.12.1
Requires-Dist: pyproj ==3.6.1
Requires-Dist: requests >=2.32.3
Requires-Dist: matplotlib ==3.9.2
Requires-Dist: rasterio ==1.4.0
Requires-Dist: rioxarray ==0.14.0
Requires-Dist: shapely >=2.0.6
Requires-Dist: progressbar2 >=4.5.0
Requires-Dist: geopandas >=1.0.1
Requires-Dist: pyyaml >=6.0.2
Requires-Dist: dask >=2024.9.0
Provides-Extra: docs
Requires-Dist: sphinx >=8.0.0 ; extra == 'docs'
Requires-Dist: myst-nb >=1.1.2 ; extra == 'docs'
Requires-Dist: sphinx-book-theme >=1.1.3 ; extra == 'docs'
Provides-Extra: download
Requires-Dist: cdsapi >=0.7.3 ; extra == 'download'
Provides-Extra: notebook
Requires-Dist: notebook >=7.2.2 ; extra == 'notebook'
